Chromasens_Python_SDK/__init__.py
Chromasens_Python_SDK/_files/__init__.py
Chromasens_Python_SDK/_files/base.py
Chromasens_Python_SDK/_files/genicam/__init__.py
Chromasens_Python_SDK/_files/genicam/genicam.py
Chromasens_Python_SDK/_files/genicam/genicam_ds.py
chromasens_python_sdk-2.0.5.dist-info/METADATA
chromasens_python_sdk-2.0.5.dist-info/WHEEL
chromasens_python_sdk-2.0.5.dist-info/licenses/LICENSE.txt
chromasens_python_sdk-2.0.5.dist-info/RECORD
